pysunvox/__init__.py
pysunvox/__main__.py
pysunvox/_core.cpython-312-darwin.so
pysunvox/sunvox.dylib
pysunvox/sunvox.py
pysunvox-0.1.1.dist-info/METADATA
pysunvox-0.1.1.dist-info/WHEEL
pysunvox-0.1.1.dist-info/entry_points.txt
pysunvox-0.1.1.dist-info/licenses/LICENSE
pysunvox-0.1.1.dist-info/RECORD
