Metadata-Version: 2.4
Name: pysunvox
Version: 0.1.1
Summary: Python bindings for the SunVox modular synthesizer library
Keywords: sunvox,synthesizer,modular,tracker,music,audio,dsp,midi
Author-Email: Shakeeb Alireza <shakfu@users.noreply.github.com>
License-Expression: MIT
Classifier: Development Status :: 4 - Beta
Classifier: Intended Audience :: Developers
Classifier: Intended Audience :: End Users/Desktop
Classifier: Operating System :: MacOS
Classifier: Operating System :: Microsoft :: Windows
Classifier: Operating System :: POSIX :: Linux
Classifier: Programming Language :: Cython
Classifier: Programming Language :: Python :: 3
Classifier: Programming Language :: Python :: 3.10
Classifier: Programming Language :: Python :: 3.11
Classifier: Programming Language :: Python :: 3.12
Classifier: Programming Language :: Python :: 3.13
Classifier: Programming Language :: Python :: 3.14
Classifier: Topic :: Multimedia :: Sound/Audio
Classifier: Topic :: Multimedia :: Sound/Audio :: MIDI
Classifier: Topic :: Multimedia :: Sound/Audio :: Sound Synthesis
Classifier: Topic :: Software Development :: Libraries :: Python Modules
Classifier: Typing :: Typed
Project-URL: Homepage, https://github.com/shakfu/pysunvox
Project-URL: Repository, https://github.com/shakfu/pysunvox
Project-URL: Issues, https://github.com/shakfu/pysunvox/issues
Requires-Python: >=3.10
